EnglishAssistantForm/Data.db
EnglishAssistantForm/EnglishAssistantForm.py
EnglishAssistantForm/SplashScreen.png
EnglishAssistantForm/__init__.py
EnglishAssistantForm/icon.ico
EnglishAssistantForm/topic_src/Art.png
EnglishAssistantForm/topic_src/Blank.png
EnglishAssistantForm/topic_src/Business.png
EnglishAssistantForm/topic_src/DataDict.json
englishassistantform-1.0.3.dist-info/METADATA
englishassistantform-1.0.3.dist-info/WHEEL
englishassistantform-1.0.3.dist-info/licenses/LICENSE.txt
englishassistantform-1.0.3.dist-info/RECORD
