Metadata-Version: 2.1
Name: EnglishAssistantForm
Version: 1.0.3
Summary: To help improve learning a language
Project-URL: Homepage, https://github.com/yasharsajadi/EnglishAssistantForm
Author-email: "Seyed Mousa Sajadi(WinCento)" <sajadimousa@gmail.com>
License-File: LICENSE.txt
Classifier: License :: OSI Approved :: MIT License
Classifier: Operating System :: OS Independent
Classifier: Programming Language :: Python :: 3
Requires-Python: >=3.10
Requires-Dist: awesometkinter==2021.11.8
Requires-Dist: customtkinter==5.2.1
Requires-Dist: englishassistantcore==1.0.6
Requires-Dist: pillow==10.1.0
Requires-Dist: requests==2.31.0
